MANIFEST.in
Makefile
README.rst
setup.cfg
setup.py
./__init__.py
./channel.py
./channel.xml
./country.py
./party.py
./product.py
./product.xml
./sale.py
./tryton.cfg
./tests/__init__.py
./tests/test_base.py
./tests/test_product.py
./tests/test_sale.py
./tests/test_views.py
./view/export_catalog_done_form.xml
./view/export_catalog_inventory_done_form.xml
./view/export_catalog_inventory_start_form.xml
./view/export_catalog_start_form.xml
./view/sale_channel_form.xml
./view/template_form.xml
./view/wizard_check_amazon_settings_view_form.xml
./view/wizard_check_service_status_view_form.xml
openlabs_amazon_mws.egg-info/PKG-INFO
openlabs_amazon_mws.egg-info/SOURCES.txt
openlabs_amazon_mws.egg-info/dependency_links.txt
openlabs_amazon_mws.egg-info/entry_points.txt
openlabs_amazon_mws.egg-info/not-zip-safe
openlabs_amazon_mws.egg-info/requires.txt
openlabs_amazon_mws.egg-info/top_level.txt