Metadata-Version: 1.1
Name: openlabs-amazon-mws
Version: 3.4.5.0
Summary: Amazon MWS Integration
Home-page: http://openlabs.co.in/
Author: Openlabs Technologies and Consulting P Ltd.
Author-email: UNKNOWN
License: GPL-3
Download-URL: https://github.com/openlabs/trytond-amazon-mws
Platform: UNKNOWN
Classifier: Development Status :: 4 - Beta
Classifier: Environment :: Plugins
Classifier: Framework :: Tryton
Classifier: Intended Audience :: Developers
Classifier: Intended Audience :: Financial and Insurance Industry
Classifier: Intended Audience :: Legal Industry
Classifier: Intended Audience :: Manufacturing
Classifier: License :: OSI Approved :: BSD License
Classifier: Natural Language :: English
Classifier: Operating System :: OS Independent
Classifier: Programming Language :: Python :: 2.7
Classifier: Topic :: Office/Business
